kognic/io/__init__.py
kognic/io/_version.py
kognic/io/client.py
kognic/io/kognicutil.py
kognic/io/logger.py
kognic/io/util.py
kognic/io/model/__init__.py
kognic/io/model/base_serializer.py
kognic/io/model/files_to_upload.py
kognic/io/model/hosts.py
kognic/io/model/upload_url.py
kognic/io/model/annotation/__init__.py
kognic/io/model/annotation/annotation.py
kognic/io/model/annotation/client_annotation.py
kognic/io/model/calibration/__init__.py
kognic/io/model/calibration/calib.py
kognic/io/model/calibration/common.py
kognic/io/model/calibration/camera/__init__.py
kognic/io/model/calibration/camera/common.py
kognic/io/model/calibration/camera/custom_camera_calibration.py
kognic/io/model/calibration/camera/cylindrical_calibration.py
kognic/io/model/calibration/camera/fisheye_calibration.py
kognic/io/model/calibration/camera/fused_cylindrical_calibration.py
kognic/io/model/calibration/camera/kannala_calibration.py
kognic/io/model/calibration/camera/pinhole_calibration.py
kognic/io/model/calibration/camera/principal_point_distortion_calibration.py
kognic/io/model/calibration/camera/principal_point_fisheye_calibration.py
kognic/io/model/calibration/lidar/__init__.py
kognic/io/model/calibration/lidar/lidar_calibration.py
kognic/io/model/ego/__init__.py
kognic/io/model/ego/imu_data.py
kognic/io/model/ego/utils.py
kognic/io/model/ego/validated_imu_data.py
kognic/io/model/ego/vehicle_pose.py
kognic/io/model/input/__init__.py
kognic/io/model/input/feature_flags.py
kognic/io/model/input/input.py
kognic/io/model/input/input_entry.py
kognic/io/model/input/input_from_scene_request.py
kognic/io/model/input/input_job.py
kognic/io/model/input/invalidated_reason_input.py
kognic/io/model/input/sensor_specification.py
kognic/io/model/input/abstract/__init__.py
kognic/io/model/input/abstract/base_frame.py
kognic/io/model/input/abstract/base_input.py
kognic/io/model/input/abstract/base_input_with_imu_data.py
kognic/io/model/input/abstract/sequence_frame.py
kognic_io-2.13.0.dist-info/METADATA
kognic_io-2.13.0.dist-info/WHEEL
kognic_io-2.13.0.dist-info/top_level.txt
kognic_io-2.13.0.dist-info/RECORD
