Metadata-Version: 2.4
Name: kognic-io
Version: 2.13.0
Summary: Kognic IO Client
Author-email: Kognic <scenes-and-predictions@kognic.com>
License: MIT
Project-URL: homepage, https://github.com/annotell/kognic-io-python
Keywords: Kognic,API
Classifier: Development Status :: 5 - Production/Stable
Classifier: License :: OSI Approved :: MIT License
Classifier: Intended Audience :: Developers
Classifier: Programming Language :: Python :: 3
Requires-Python: >=3.10
Requires-Dist: kognic-auth<4,>=3.0.0
Requires-Dist: kognic-openlabel<3,>=2.0.0
Requires-Dist: kognic-base-clients<3,>=2.3.4
Requires-Dist: click>=7.1.1
Requires-Dist: requests<3,>=2.23.0
Requires-Dist: tabulate>=0.8.7
Requires-Dist: python-dateutil
Requires-Dist: pydantic<3,>=2
Requires-Dist: Deprecated
Requires-Dist: tqdm
Provides-Extra: wasm
Requires-Dist: wasmtime<13; extra == "wasm"
